cli.py
tpyl/__init__.py
tpyl/filters.py
tpyl/parse.py
tpyl/rendering.py
tpyl/utils.py
tpyl-0.1.dist-info/METADATA
tpyl-0.1.dist-info/WHEEL
tpyl-0.1.dist-info/entry_points.txt
tpyl-0.1.dist-info/top_level.txt
tpyl-0.1.dist-info/RECORD
